nemonet/__init__.py
nemonet/cvision/__init__.py
nemonet/cvision/computer_vision.py
nemonet/engines/__init__.py
nemonet/engines/cache_store.py
nemonet/engines/graph.py
nemonet/engines/sequencer.py
nemonet/main.py
nemonet/runner/__init__.py
nemonet/runner/runner.py
nemonet/runner/tool.py
nemonet/runner/webdriver.py
nemonet/screencast/__init__.py
nemonet/screencast/recording.py
nemonet/screencast/store.py
nemonet/screencast/web_screen.py
nemonet/seleniumwebdriver/__init__.py
nemonet/seleniumwebdriver/abstract_command.py
nemonet/seleniumwebdriver/command_list.py
nemonet/seleniumwebdriver/commands.py
nemonet/seleniumwebdriver/page_capture.py
nemonet/tests/27fa42f6-e7d9-44e2-8cea-01d768dff139.zip
nemonet/tests/5530861d-8887-4c38-8a6c-7fc30ac07b6a.zip
nemonet/tests/__init__.py
nemonet/tests/command-current-pos.xml
nemonet/tests/command-get_value.xml
nemonet/tests/command-get_value_and_store.xml
nemonet/tests/command-right-mouse.xml
nemonet/tests/command-screenshot-avi.xml
nemonet/tests/command-sel_exists.xml
nemonet/tests/command-set-env-setup.xml
nemonet/tests/command-set-env.xml
nemonet/tests/command-tab-and-text.xml
nemonet/tests/command-tabs.xml
nemonet/tests/commands-double-mouse-click.xml
nemonet/tests/commands-drag-and-drop-mouse.xml
nemonet/tests/commands-drag-and-drop-offset.xml
nemonet/tests/commands-drag-and-drop.xml
nemonet/tests/commands-explicit-waits.xml
nemonet/tests/commands-plugins.xml
nemonet/tests/commands-reformat-url.xml
nemonet/tests/commands-remove-html-element.xml
nemonet/tests/commands-save-records.xml
nemonet/tests/commands-site-settings.xml
nemonet/tests/dummy.xml
nemonet/tests/graph-screen-type.xml
nemonet/tests/test_commands.py
nemonet/tests/test_plugin_command.py
nemonet/tests/test_remote_driver.py
nemonet/tests/units/__init__.py
nemonet/tests/units/graph-screen-type.xml
nemonet/tests/units/plugin/__init__.py
nemonet/tests/units/plugin/vision_my_custom_1.py
nemonet/tests/units/plugin/vision_my_custom_2.py
nemonet-0.18.9.dist-info/entry_points.txt
nemonet-0.18.9.dist-info/LICENSE
nemonet-0.18.9.dist-info/METADATA
nemonet-0.18.9.dist-info/WHEEL
nemonet-0.18.9.dist-info/RECORD
