Metadata-Version: 2.1
Name: nemonet
Version: 0.18.9
Summary: Visual testing framework. Combining selenium and computer vision.
License: MIT
Author: Jan Rummens
Author-email: jan.rummens@nemo.be
Requires-Python: >=3.10,<4.0
Classifier: License :: OSI Approved :: MIT License
Classifier: Programming Language :: Python :: 3
Classifier: Programming Language :: Python :: 3.10
Classifier: Programming Language :: Python :: 3.11
Classifier: Programming Language :: Python :: 3.12
Requires-Dist: beautifulsoup4 (>=4.12.2,<5.0.0)
Requires-Dist: chardet (>=5.2.0,<6.0.0)
Requires-Dist: graphviz (>=0.20.1,<0.21.0)
Requires-Dist: h5py (>=3.10.0,<4.0.0)
Requires-Dist: imagehash (>=4.3.1,<5.0.0)
Requires-Dist: imutils (>=0.5.4,<0.6.0)
Requires-Dist: lxml (>=4.9.3,<5.0.0)
Requires-Dist: opencv-python (>=4.8.1.78,<5.0.0.0)
Requires-Dist: pillow (>=10.1.0,<11.0.0)
Requires-Dist: scikit-image (>=0.22.0,<0.23.0)
Requires-Dist: selenium (>=4.15.2,<5.0.0)
Requires-Dist: typer (>=0.9.0,<0.10.0)
